{
  "trading": {
    "initial_capital": 1000,
    "max_position_size": 0.15,
    "stop_loss": 0.03,
    "take_profit": 0.08,
    "live_trading": {
      "enabled": true,
      "check_interval": 180,
      "market_hours_only": true,
      "max_trades_per_day": 8,
      "min_trade_interval": 300,
      "risk_per_trade": 0.015,
      "max_daily_loss": 0.05
    },
    "risk_management": {
      "max_portfolio_risk": 0.20,
      "max_correlation": 0.7,
      "diversification_min": 3,
      "emergency_stop_loss": 0.10
    }
  },
  "news_trading": {
    "enabled": true,
    "weight": 0.3,
    "sentiment_threshold": 0.15,
    "news_impact_decay": 24,
    "max_news_positions": 0.25,
    "rss_feeds": {
      "marketwatch_pulse": "https://feeds.content.dowjones.io/public/rss/mw_marketpulse",
      "investing_com": "https://www.investing.com/rss/news.rss",
      "reuters_business": "http://feeds.reuters.com/reuters/businessNews",
      "yahoo_finance_aapl": "https://feeds.finance.yahoo.com/rss/2.0/headline?s=AAPL&region=US&lang=en-US",
      "cnbc_markets": "https://www.cnbc.com/id/15839135/device/rss/rss.html",
      "seeking_alpha": "https://seekingalpha.com/feed.xml",
      "bloomberg": "https://feeds.bloomberg.com/markets/news.rss",
      "marketwatch": "https://www.marketwatch.com/rss/topstories",
      "finviz": "https://finviz.com/news.ashx?c=1",
      "benzinga": "https://www.benzinga.com/rss/benzinga"
    },
    "update_interval": 600,
    "min_update_interval": 300,
    "user_agent": "StockAI-NewsBot/2.0 (+https://github.com/risik01/stock-ai)",
    "request_timeout": 30,
    "max_retries": 3,
    "etag_cache": true
  },
  "ai_trading": {
    "enabled": true,
    "model_confidence_threshold": 0.65,
    "ensemble_voting": true,
    "models": {
      "sentiment_analyzer": {
        "enabled": true,
        "weight": 0.25
      },
      "technical_analyzer": {
        "enabled": true,
        "weight": 0.35
      },
      "rl_agent": {
        "enabled": true,
        "weight": 0.40
      }
    },
    "decision_cooldown": 300,
    "max_ai_trades_per_hour": 2
  },
  "rl_agent": {
    "learning_rate": 0.001,
    "discount_factor": 0.95,
    "epsilon": 0.1,
    "epsilon_decay": 0.995,
    "epsilon_min": 0.01,
    "batch_size": 32,
    "memory_size": 10000,
    "training_frequency": 100,
    "target_update_frequency": 1000
  },
  "data": {
    "update_interval": 60,
    "lookback_days": 90,
    "symbols": [
      "AAPL",
      "GOOGL", 
      "MSFT",
      "TSLA",
      "AMZN",
      "META",
      "NVDA"
    ],
    "real_time": {
      "enabled": true,
      "source": "yfinance",
      "refresh_rate": 30
    }
  },
  "monitoring": {
    "price_alerts": true,
    "volume_alerts": true,
    "news_alerts": true,
    "performance_alerts": true,
    "technical_indicators": ["RSI", "MACD", "BB", "EMA", "SMA"],
    "alert_thresholds": {
      "rsi_oversold": 25,
      "rsi_overbought": 75,
      "volume_spike": 1.8,
      "price_change": 0.05,
      "daily_loss": 0.03
    }
  },
  "logging": {
    "level": "INFO",
    "max_file_size": "10MB",
    "backup_count": 5,
    "detailed_trades": true,
    "performance_tracking": true
  },
  "notifications": {
    "email_enabled": false,
    "webhook_enabled": false,
    "console_enabled": true,
    "file_logging": true
  },
  "safety": {
    "paper_trading_mode": false,
    "require_confirmation": false,
    "max_daily_trades": 10,
    "cooling_off_period": 3600,
    "emergency_stop_enabled": true,
    "max_consecutive_losses": 5
  }
}
